bubblegum/__init__.py
bubblegum/__main__.py
bubblegum/config.py
bubblegum/database.py
bubblegum/errors.py
bubblegum/hosts.py
bubblegum/profiles.py
bubblegum-1.0.1.dist-info/entry_points.txt
bubblegum-1.0.1.dist-info/LICENSE
bubblegum-1.0.1.dist-info/WHEEL
bubblegum-1.0.1.dist-info/METADATA
bubblegum-1.0.1.dist-info/RECORD
