Metadata-Version: 2.1
Name: bubblegum
Version: 1.0.1
Summary: A script to make and manage uploads to image hosts.
Home-page: https://github.com/azuline/bubblegum
License: Apache-2.0
Keywords: image-uploader
Author: azuline
Author-email: azuline@riseup.net
Requires-Python: >=3.6,<4.0
Classifier: License :: OSI Approved :: Apache Software License
Classifier: Programming Language :: Python :: 3
Classifier: Programming Language :: Python :: 3.6
Classifier: Programming Language :: Python :: 3.7
Classifier: Programming Language :: Python :: 3.8
Requires-Dist: appdirs (>=1.4,<2.0)
Requires-Dist: click (>=7.0,<8.0)
Requires-Dist: pyperclip (>=1.8.1,<2.0.0)
Requires-Dist: requests (>=2.0,<3.0)
Project-URL: Repository, https://github.com/azuline/bubblegum
